{
  "queryDefinitionId": "d4fbfc35-475c-4e83-bc61-90441f4cabf7",
  "name": "Qr_Resultados_Excluidos_Prospect_Online_ComOTC_NeoBpo_Pub4",
  "key": "e8a71479-7c60-4ea1-9f82-b1d80bfb3a08",
  "description": "",
  "queryText": "SELECT\n  ORIGEM.CPF as CPF_CNPJ,\n  CMP.NAME AS CAMPANHA,\n  /* PAR.HC_CODIGO_DO_PARCEIRO_CAP__C AS PARCEIRO, */\n  /* CONVERT(INTEGER, REL.HC_IDADE__C) AS  IDADE, */\n  /* DATEDIFF(YY,\n  CAST(ORIGEM.DATA_NASCIMENTO AS DATE),\n  GETDATE()) AS IDADE, */\n  /* ORIGEM.COMPRA_UTIMOS_30_DIAS AS COMPROU_ULTIMOS_30_DIAS, */\n  /* ORIGEM.CLIENTE_PEP, */\n  /* ORIGEM.CLIENTE, */\n  /* ORIGEM.CONSELHEIRO, */\n  /* ORIGEM.DESEJA_CONTATO_TELEFONICO AS NAO_DESEJA_RECEBER_LIGACOES, */\n  /* ORIGEM.POSSUI_TELEFONE_ATIVO, */\n  /* ORIGEM.POSSUI_CONTA_CORRENTE, */\n  /* ORIGEM.CONTA_CORRENTE AS POSSUI_CONTA_CORRENTE, */\n  /* ORIGEM.POSSUI_TITULO_ATIVO, */\n  /* ORIGEM.QUARENTENA, */\n  /* ORIGEM.NAO_IMPORTUNE, */\n  /* ORIGEM.CEP_VALIDO, */\n  OTC291.ALTA_RENDA,\n  /* OTC291.ENCARTEIRAMENTO_VALIDO, */\n  CASE\n    WHEN OTC291.CODIGO_RNA IS NULL OR OTC291.CODIGO_RNA != '000' THEN 'EXCLUIDO RNA'\n    WHEN OTC291.ALTA_RENDA IS NULL OR OTC291.ALTA_RENDA != 0 THEN 'ALTA RENDA'\n    /* WHEN (OTC291.ENCARTEIRAMENTO_VALIDO IS NULL OR OTC291.ENCARTEIRAMENTO_VALIDO != 1) THEN 'ENCARTEIRAMENTO INVALIDO' */\n  END AS RESULTADO\nFROM TB_BASE_PROSPECT_OTC291_ONLINE_TRATADA_NEOBPO_PUB4 OTC291\nINNER JOIN TB_BASE_PROSPECT_COMOTC_ONLINE_TRATADA_NEOBPO_PUB1 ORIGEM ON ORIGEM.cpf = OTC291.CPF\nLEFT JOIN CAMPAIGN_SALESFORCE CMP ON ORIGEM.ID_CAMPANHA = CMP.ID\n\nWHERE \n  (OTC291.CODIGO_RNA IS NULL OR OTC291.CODIGO_RNA != '000')\n  OR (OTC291.ALTA_RENDA IS NULL OR OTC291.ALTA_RENDA != 0)\n  /* OR (OTC291.ENCARTEIRAMENTO_VALIDO IS NULL OR OTC291.ENCARTEIRAMENTO_VALIDO != 1) */",
  "targetName": "Tb_Log_Resultados_de_Avaliacao",
  "targetKey": "88231EFF-D3C6-4EF4-BE12-BA0197BC551D",
  "targetId": "57b988f5-a2e5-eb11-a304-48df37342b90",
  "targetDescription": "Resultados de contatos que nao foram aptos para entrar na jornada",
  "createdDate": "2022-02-17T05:09:58.68",
  "modifiedDate": "2022-02-17T05:09:58.68",
  "targetUpdateTypeId": 2,
  "targetUpdateTypeName": "Append",
  "categoryId": 1930,
  "isFrozen": false
}