[
  {
    "Name": "Nome",
    "FieldType": "Text",
    "ObjectID": "56014c5b-b98c-4709-8cd5-73fe58632d3a",
    "MaxLength": "300",
    "Scale": "0",
    "IsRequired": "false",
    "IsPrimaryKey": "false",
    "DefaultValue": "",
    "Ordinal": 0
  },
  {
    "Name": "Telefone",
    "FieldType": "Phone",
    "ObjectID": "58830afb-b443-4609-8e96-07b0fe3c2a13",
    "MaxLength": "50",
    "Scale": "0",
    "IsRequired": "true",
    "IsPrimaryKey": "false",
    "DefaultValue": "",
    "Ordinal": 1
  },
  {
    "Name": "ID",
    "FieldType": "Text",
    "ObjectID": "bed24780-6957-4e05-bced-8d716a005c49",
    "MaxLength": "200",
    "Scale": "0",
    "IsRequired": "true",
    "IsPrimaryKey": "true",
    "DefaultValue": "",
    "Ordinal": 2
  },
  {
    "Name": "locale",
    "FieldType": "Locale",
    "ObjectID": "3048383b-8c3c-4a5e-a2e7-24538f4070cc",
    "MaxLength": "5",
    "Scale": "0",
    "IsRequired": "true",
    "IsPrimaryKey": "false",
    "DefaultValue": "",
    "Ordinal": 3
  }
]